{
	"configurations" : 
	[
		{
			"directories" : 
			[
				{
					"build" : ".",
					"jsonFile" : "directory-.-MinSizeRel-d0094a50bb2071803777.json",
					"minimumCMakeVersion" : 
					{
						"string" : "3.22"
					},
					"projectIndex" : 0,
					"source" : ".",
					"targetIndexes" : 
					[
						0
					]
				}
			],
			"name" : "MinSizeRel",
			"projects" : 
			[
				{
					"directoryIndexes" : 
					[
						0
					],
					"name" : "ProjetS4SDL2",
					"targetIndexes" : 
					[
						0
					]
				}
			],
			"targets" : 
			[
				{
					"directoryIndex" : 0,
					"id" : "ProjetS4SDL2::@6890427a1f51a3e7e1df",
					"jsonFile" : "target-ProjetS4SDL2-MinSizeRel-ce11566671dee525be2d.json",
					"name" : "ProjetS4SDL2",
					"projectIndex" : 0
				}
			]
		}
	],
	"kind" : "codemodel",
	"paths" : 
	{
		"build" : "C:/Users/nolan/OneDrive/Documents/Git/ProjetS4SDL2/cmake-build-minsizerel",
		"source" : "C:/Users/nolan/OneDrive/Documents/Git/ProjetS4SDL2"
	},
	"version" : 
	{
		"major" : 2,
		"minor" : 6
	}
}
